kale/__init__.py
kale/cli.py
kale/compiler.py
kale/pipeline.py
kale/step.py
kale/common/__init__.py
kale/common/astutils.py
kale/common/flakeutils.py
kale/common/graphutils.py
kale/common/jputils.py
kale/common/k8sutils.py
kale/common/katibutils.py
kale/common/kfputils.py
kale/common/kfutils.py
kale/common/logutils.py
kale/common/mlmdutils.py
kale/common/podutils.py
kale/common/rokutils.py
kale/common/runutils.py
kale/common/serveutils.py
kale/common/utils.py
kale/common/workflowutils.py
kale/config/__init__.py
kale/config/config.py
kale/config/validators.py
kale/kfserving/__init__.py
kale/kfserving/__main__.py
kale/kfserving/transformer.py
kale/marshal/__init__.py
kale/marshal/backend.py
kale/marshal/backends.py
kale/marshal/decorator.py
kale/processors/__init__.py
kale/processors/baseprocessor.py
kale/processors/nbprocessor.py
kale/processors/pyprocessor.py
kale/rpc/errors.py
kale/rpc/katib.py
kale/rpc/kfp.py
kale/rpc/log.py
kale/rpc/nb.py
kale/rpc/rok.py
kale/rpc/run.py
kale/rpc/utils.py
kale/sdk/__init__.py
kale/sdk/api.py
kale/templates/nb_function_template.jinja2
kale/templates/pipeline_template.jinja2
kale/templates/py_function_template.jinja2
kubeflow_kale-0.7.0.dist-info/METADATA
kubeflow_kale-0.7.0.dist-info/WHEEL
kubeflow_kale-0.7.0.dist-info/entry_points.txt
kubeflow_kale-0.7.0.dist-info/top_level.txt
kubeflow_kale-0.7.0.dist-info/RECORD
